{"file":"daycare-xTCL2ANB.js","mappings":"AAAO,SAAS,gBAAgB,OAA8B;AAC5D,MAAI,CAAC,MAAO,QAAO;AACnB,MAAI,iBAAiB,KAAM,QAAO,OAAO,MAAM,MAAM,QAAA,CAAS,IAAI,OAAO;AAEzE,QAAM,SAAS,OAAO,KAAK,EAAE,KAAA;AAC7B,QAAM,WAAW,2BAA2B,KAAK,MAAM;AACvD,MAAI,UAAU;AACZ,UAAM,GAAG,MAAM,OAAO,GAAG,IAAI;AAC7B,WAAO,IAAI,KAAK,OAAO,IAAI,GAAG,OAAO,KAAK,IAAI,GAAG,OAAO,GAAG,CAAC;AAAA,EAC9D;AAEA,QAAM,aAAa,OAAO,SAAS,GAAG,IAAI,OAAO,QAAQ,KAAK,GAAG,IAAI;AACrE,QAAM,OAAO,IAAI,KAAK,UAAU;AAChC,SAAO,OAAO,MAAM,KAAK,QAAA,CAAS,IAAI,OAAO;AAC/C;AAEO,SAAS,WAAW,OAA8B,WAAW,aAAa;AAC/E,QAAM,OAAO,gBAAgB,KAAK;AAClC,MAAI,CAAC,QAAQ,KAAK,YAAA,IAAgB,IAAM,QAAO;AAC/C,SAAO,IAAI,KAAK,eAAe,SAAS;AAAA,IACtC,KAAK;AAAA,IACL,OAAO;AAAA,IACP,MAAM;AAAA,EAAA,CACP,EAAE,OAAO,IAAI;AAChB;AAEO,SAAS,kBAAkB,OAA8B;AAC9D,QAAM,OAAO,gBAAgB,KAAK;AAClC,MAAI,CAAC,KAAM,QAAO,EAAE,KAAK,KAAK,SAAS,IAAI,OAAO,GAAA;AAClD,SAAO;AAAA,IACL,KAAK,IAAI,KAAK,eAAe,SAAS,EAAE,KAAK,UAAA,CAAW,EAAE,OAAO,IAAI;AAAA,IACrE,SAAS,IAAI,KAAK,eAAe,SAAS,EAAE,SAAS,OAAA,CAAQ,EAAE,OAAO,IAAI;AAAA,IAC1E,OAAO,IAAI,KAAK,eAAe,SAAS,EAAE,OAAO,OAAA,CAAQ,EAAE,OAAO,IAAI;AAAA,EAAA;AAE1E;AAEO,SAAS,gBAAgB,UAA0B;AACxD,SAAO,QAAQ,YAAY,8BAA8B,KAAK,QAAQ,CAAC;AACzE;AAEO,SAAS,cAAc,UAA0B;AACtD,SAAO,QAAQ,YAAY,iBAAiB,KAAK,QAAQ,CAAC;AAC5D;AAEO,SAAS,UAAU,OAAuB;AAC/C,UAAQ,SAAS,IAAI,QAAQ,YAAY,GAAG,EAAE,QAAQ,QAAQ,GAAG,EAAE,KAAA;AACrE;AAEO,SAAS,sBAAsB,UAA0B;AAC9D,MAAI,CAAC,SAAU,QAAO;AACtB,MAAI,gBAAgB,KAAK,QAAQ,EAAG,QAAO;AAC3C,MAAI,SAAS,WAAW,WAAW,EAAG,QAAO;AAC7C,QAAM,WAAW,SAAS,MAAM,GAAG,EAAE,IAAA,GAAO,MAAM,GAAG,EAAE,CAAC,GAAG,MAAM,GAAG,EAAE,CAAC;AACvE,MAAI,CAAC,SAAU,QAAO;AACtB,SAAO,+DAA+D,mBAAmB,YAAY,QAAQ,EAAE,CAAC;AAClH;AAEO,SAAS,yBAAyB,KAAqB;AAC5D,QAAM,QAAQ,OAAO,OAAO,EAAE,EAAE,KAAA;AAChC,MAAI,CAAC,MAAO,QAAO;AACnB,MAAI,gBAAgB,KAAK,KAAK,KAAK,MAAM,WAAW,OAAO,KAAK,MAAM,WAAW,GAAG,EAAG,QAAO;AAC9F,SAAO,4CAA4C,MAAM,QAAQ,iBAAiB,EAAE,CAAC;AACvF;AAEO,SAAS,sBAAsB,QAAgB;AACpD,SAAO,WAAW,IAAI,iBAAiB,WAAW,MAAM;AAC1D;AA2BO,SAAS,iBAAiB,OAAgB;AAC/C,SAAO,UAAU,QAAQ,UAAU,KAAK,OAAO,KAAK,MAAM,OAAO,OAAO,KAAK,EAAE,YAAA,MAAkB;AACnG;AASO,SAAS,uBAAuB,MAAsB;AAC3D,MAAI,SAAS,KAAM,QAAO;AAC1B,MAAI,SAAS,OAAQ,QAAO;AAC5B,MAAI,SAAS,MAAO,QAAO;AAC3B,SAAO;AACT;","names":[],"sources":["../../../../utils/daycare.ts"],"sourcesContent":["export function parseLegacyDate(value?: string | Date | null) {\n  if (!value) return null\n  if (value instanceof Date) return Number.isNaN(value.getTime()) ? null : value\n\n  const source = String(value).trim()\n  const dateOnly = /^(\\d{4})-(\\d{2})-(\\d{2})/.exec(source)\n  if (dateOnly) {\n    const [, year, month, day] = dateOnly\n    return new Date(Number(year), Number(month) - 1, Number(day))\n  }\n\n  const normalized = source.includes(' ') ? source.replace(' ', 'T') : source\n  const date = new Date(normalized)\n  return Number.isNaN(date.getTime()) ? null : date\n}\n\nexport function formatDate(value?: string | Date | null, fallback = 'Sin fecha') {\n  const date = parseLegacyDate(value)\n  if (!date || date.getFullYear() < 2000) return fallback\n  return new Intl.DateTimeFormat('es-MX', {\n    day: '2-digit',\n    month: 'long',\n    year: 'numeric'\n  }).format(date)\n}\n\nexport function formatCalendarDay(value?: string | Date | null) {\n  const date = parseLegacyDate(value)\n  if (!date) return { day: '—', weekday: '', month: '' }\n  return {\n    day: new Intl.DateTimeFormat('es-MX', { day: '2-digit' }).format(date),\n    weekday: new Intl.DateTimeFormat('es-MX', { weekday: 'long' }).format(date),\n    month: new Intl.DateTimeFormat('es-MX', { month: 'long' }).format(date)\n  }\n}\n\nexport function isImageResource(resource?: string | null) {\n  return Boolean(resource && /\\.(png|jpe?g|webp)(\\?|#|$)/i.test(resource))\n}\n\nexport function isPdfResource(resource?: string | null) {\n  return Boolean(resource && /\\.pdf(\\?|#|$)/i.test(resource))\n}\n\nexport function stripHtml(value?: string | null) {\n  return (value || '').replace(/<[^>]*>/g, ' ').replace(/\\s+/g, ' ').trim()\n}\n\nexport function publishedPdfViewerUrl(resource?: string | null) {\n  if (!resource) return ''\n  if (/^https?:\\/\\//i.test(resource)) return resource\n  if (resource.startsWith('/uploads/')) return resource\n  const fileName = resource.split('/').pop()?.split('#')[0]?.split('?')[0]\n  if (!fileName) return resource\n  return `https://admin.casitaiedis.edu.mx/pdfjs/web/viewer.html?file=${encodeURIComponent(`/virtual/${fileName}`)}`\n}\n\nexport function normalizeVirtualAssetUrl(url?: string | null) {\n  const value = String(url || '').trim()\n  if (!value) return ''\n  if (/^https?:\\/\\//i.test(value) || value.startsWith('data:') || value.startsWith('/')) return value\n  return `https://admin.casitaiedis.edu.mx/virtual/${value.replace(/^\\/?virtual\\//, '')}`\n}\n\nexport function authorizedPersonLabel(indice: number) {\n  return indice === 4 ? 'Pase Express' : `Persona ${indice}`\n}\n\nexport function appAbsoluteUrl(path: string) {\n  if (typeof window === 'undefined') return path\n  return `${window.location.origin}${path}`\n}\n\nexport function authorizedPersonValidationPath(id?: number | string | null) {\n  return id ? `/validar/persona-autorizada/${id}` : ''\n}\n\nexport function authorizedPersonQrPath(id?: number | string | null) {\n  return id ? `/familia/personas-autorizadas/${id}/qr` : ''\n}\n\nexport function authorizedPersonCredentialPath(id?: number | string | null) {\n  return id ? `/familia/personas-autorizadas/${id}/credencial` : ''\n}\n\nexport function authorizedPersonPrintPath(id?: number | string | null) {\n  return id ? `/familia/personas-autorizadas/${id}/imprimir` : ''\n}\n\nexport function authorizedPersonMarbetePath(id?: number | string | null) {\n  return id ? `/familia/personas-autorizadas/${id}/marbete` : ''\n}\n\nexport function isHiddenResource(value: unknown) {\n  return value === true || value === 1 || String(value) === '1' || String(value).toLowerCase() === 'hidden'\n}\n\nexport function daycareResourceTypeLabel(type?: string | null) {\n  if (type === 'hw') return 'Tarea'\n  if (type === 'news') return 'Aviso'\n  if (type === 'cal') return 'Evento'\n  return 'Contenido'\n}\n\nexport function daycareResourceSection(type?: string | null) {\n  if (type === 'hw') return 'tareas'\n  if (type === 'news') return 'avisos'\n  if (type === 'cal') return 'calendario'\n  return ''\n}\n"],"version":3}